{
   "data":{
      "id":"1001",
      "type":"persons",
      "attributes":{
         "name":"Bart"
      },
      "relationships":{
         "sister":{
            "data":{
              "id":"1002",
              "type":"persons"
            }
         },
         "father":{
            "data":{
              "id":"998",
              "type":"persons"
            }
         }
      }
   },
   "included":[
      {
         "id":"1002",
         "type":"persons",
         "attributes":{
            "name":"Lisa"
         }
      },
      {
         "id":"998",
         "type":"persons",
         "attributes":{
            "name":"Homer"
         },
         "relationships":{
            "car":{
               "data":{
                  "id":"1002",
                  "type":"car"
               }
            }
         }
      },
      {
         "id":"1002",
         "type":"car",
         "attributes":{
            "name":"PinkSedan"
         }
      }
   ]
}
